cloudshell/__init__.py
cloudshell/cp/__init__.py
cloudshell/cp/kubernetes/__init__.py
cloudshell/cp/kubernetes/resource_config.py
cloudshell/cp/kubernetes/common/__init__.py
cloudshell/cp/kubernetes/common/additional_data_keys.py
cloudshell/cp/kubernetes/common/utils.py
cloudshell/cp/kubernetes/flows/__init__.py
cloudshell/cp/kubernetes/flows/autoload.py
cloudshell/cp/kubernetes/flows/cleanup.py
cloudshell/cp/kubernetes/flows/delete.py
cloudshell/cp/kubernetes/flows/deploy.py
cloudshell/cp/kubernetes/flows/power.py
cloudshell/cp/kubernetes/flows/prepare.py
cloudshell/cp/kubernetes/flows/refresh_ip.py
cloudshell/cp/kubernetes/flows/vm_details.py
cloudshell/cp/kubernetes/models/__init__.py
cloudshell/cp/kubernetes/models/clients.py
cloudshell/cp/kubernetes/models/deploy_app.py
cloudshell/cp/kubernetes/models/deployed_app.py
cloudshell/cp/kubernetes/models/deployment_requests.py
cloudshell/cp/kubernetes/services/__init__.py
cloudshell/cp/kubernetes/services/clients.py
cloudshell/cp/kubernetes/services/deployment.py
cloudshell/cp/kubernetes/services/namespace.py
cloudshell/cp/kubernetes/services/networking.py
cloudshell/cp/kubernetes/services/service_provider.py
cloudshell/cp/kubernetes/services/tags.py
cloudshell/cp/kubernetes/services/vm_details.py
tests/__init__.py
tests/cloudshell/__init__.py
tests/cloudshell/cp/__init__.py
tests/cloudshell/cp/kubernetes/__init__.py
tests/cloudshell/cp/kubernetes/test_resource_config.py
cloudshell_cp_kubernetes-1.0.18.dist-info/METADATA
cloudshell_cp_kubernetes-1.0.18.dist-info/WHEEL
cloudshell_cp_kubernetes-1.0.18.dist-info/top_level.txt
cloudshell_cp_kubernetes-1.0.18.dist-info/RECORD
